django_secrets/__init__.py
django_secrets/management/__init__.py
django_secrets/management/commands/__init__.py
django_secrets/management/commands/export_secrets.py
django_secrets/settings.py
django_secrets/startup.py
django_secrets/tests.py
django_secrets/urls.py
django_secrets/utils.py
django_secrets/wsgi.py
django_secrets-2.0.1.dist-info/LICENSE
django_secrets-2.0.1.dist-info/METADATA
django_secrets-2.0.1.dist-info/WHEEL
django_secrets-2.0.1.dist-info/RECORD
