Metadata-Version: 2.3
Name: django_secrets
Version: 2.0.1
Summary: 
License: MIT
Author: Andy Grabow
Author-email: andy@freilandkiwis.de
Requires-Python: >=3.9,<4.0
Classifier: License :: OSI Approved :: MIT License
Classifier: Programming Language :: Python :: 3
Classifier: Programming Language :: Python :: 3.9
Classifier: Programming Language :: Python :: 3.10
Classifier: Programming Language :: Python :: 3.11
Classifier: Programming Language :: Python :: 3.12
Classifier: Programming Language :: Python :: 3.13
Requires-Dist: Django (>=2.2.27)
Requires-Dist: six (>=1.11,<2.0)
